lingtaiAgent/__init__.py
lingtaiAgent/lingtai.py
lingtaiagent-0.0.5.dist-info/licenses/LICENSE
lingtaiagent-0.0.5.dist-info/METADATA
lingtaiagent-0.0.5.dist-info/WHEEL
lingtaiagent-0.0.5.dist-info/top_level.txt
lingtaiagent-0.0.5.dist-info/RECORD
