Metadata-Version: 2.4
Name: lingtaiAgent
Version: 0.0.5
Summary: 灵台客户端包
Home-page: https://www.bailongma.com
Author: jiayifei
Author-email: jiayifei@bailongma-inc.com
Classifier: Programming Language :: Python :: 3
Classifier: License :: OSI Approved :: MIT License
Classifier: Operating System :: OS Independent
Requires-Python: >=3.6
License-File: LICENSE
Requires-Dist: requests>=2.25
Dynamic: license-file
